{
  "hash": "194dd677",
  "configHash": "f1cd09b4",
  "lockfileHash": "be5b0348",
  "browserHash": "8f479f1c",
  "optimized": {
    "react": {
      "src": "../../node_modules/react/index.js",
      "file": "react.js",
      "fileHash": "9f281de4",
      "needsInterop": true
    },
    "react-dom/client": {
      "src": "../../node_modules/react-dom/client.js",
      "file": "react-dom_client.js",
      "fileHash": "eef3009a",
      "needsInterop": true
    },
    "react-router-dom": {
      "src": "../../node_modules/react-router-dom/dist/index.js",
      "file": "react-router-dom.js",
      "fileHash": "b7a4405c",
      "needsInterop": false
    },
    "firebase/firestore": {
      "src": "../../node_modules/firebase/firestore/dist/esm/index.esm.js",
      "file": "firebase_firestore.js",
      "fileHash": "7ab543e8",
      "needsInterop": false
    },
    "firebase/app": {
      "src": "../../node_modules/firebase/app/dist/esm/index.esm.js",
      "file": "firebase_app.js",
      "fileHash": "fbdea3a8",
      "needsInterop": false
    },
    "firebase/auth": {
      "src": "../../node_modules/firebase/auth/dist/esm/index.esm.js",
      "file": "firebase_auth.js",
      "fileHash": "582b8939",
      "needsInterop": false
    }
  },
  "chunks": {
    "chunk-QHHSQPNG": {
      "file": "chunk-QHHSQPNG.js"
    },
    "chunk-HCGKX5ED": {
      "file": "chunk-HCGKX5ED.js"
    },
    "chunk-WNPTCGAH": {
      "file": "chunk-WNPTCGAH.js"
    },
    "chunk-5WRI5ZAA": {
      "file": "chunk-5WRI5ZAA.js"
    }
  }
}